{
  "bindings": [
    {
      "authLevel": "anonymous",
      "type": "httpTrigger",
      "direction": "in",
      "name": "req",
      "methods": [
        "get"
      ],
      "route": "course"
    },
    {
      "type": "http",
      "direction": "out",
      "name": "res"
    },
    {
      "type": "cosmosDB",
      "direction": "in",
      "name": "inputCourses",
      "databaseName": "firedlabs",
      "collectionName": "courses",
      "connectionStringSetting": "firedlabs_DOCUMENTDB"
    }
  ]
}
